sparta_spanner-0.2.1-py3.9-nspkg.pth
sparta/spanner/__init__.py
sparta/spanner/concurrency.py
sparta/spanner/provider.py
sparta/spanner/service.py
sparta/spanner/utils.py
sparta_spanner-0.2.1.dist-info/LICENSE
sparta_spanner-0.2.1.dist-info/METADATA
sparta_spanner-0.2.1.dist-info/WHEEL
sparta_spanner-0.2.1.dist-info/namespace_packages.txt
sparta_spanner-0.2.1.dist-info/top_level.txt
sparta_spanner-0.2.1.dist-info/RECORD
