Metadata-Version: 2.1
Name: sparta-spanner
Version: 0.2.1
Summary: Sparta spanner library
Home-page: https://github.com/Spartan-Approach/sparta-spanner
Author: Spartan Approach
Author-email: sparta@spartanapproach.com
License: UNKNOWN
Platform: UNKNOWN
Classifier: Development Status :: 4 - Beta
Classifier: Programming Language :: Python :: 3
Classifier: License :: OSI Approved :: MIT License
Classifier: Operating System :: OS Independent
Requires-Python: >=3.9
License-File: LICENSE
Requires-Dist: google-cloud-spanner ==3.22.2
Provides-Extra: test
Requires-Dist: pytest ; extra == 'test'
Requires-Dist: pytest-asyncio ; extra == 'test'
Requires-Dist: python-dotenv ; extra == 'test'
